{
  "id": "Revelation-Options",
  "titles": {
    "kr": "페르소나5X 계시 옵션에 대해",
    "en": "About Persona 5X Revelation Stats",
    "jp": "ペルソナ5X 啓示のオプションについて"
  },
  "excerpts": {
    "kr": "모든 스탯 수치는 레벨 1부터 레벨 25까지 노란색 계시 카드를 기준으로 한다. 주 옵션 (Main Stats) 각 계시 위치 별로 나올 수 있는 주 옵션이 고정돼 있다. 위치옵션주 (Universe)공격력, 방어력일 (Sun)생명월 (Moon)공격력, 대미지 보너스,...",
    "en": "Stats are based on the yellow revelation cards starting at Lv1 to Lv25 Main Stats Each revelation position has fixed main stats that can appear. Posit...",
    "jp": "すべてのステータスの数値はレベル1からレベル25までの黄色の啓示カードを基準にしています。 メインステータス 各啓示のポジション別に出現可能な主属性が固定されています。 ポジションオプション主 (Universe)攻撃力、防御力旭 (Sun)HP月 (Moon)攻撃力、攻撃倍率+、HP、防御力、HP..."
  },
  "searchContent": {
    "kr": "모든 스탯 수치는 레벨 1부터 레벨 25까지 노란색 계시 카드를 기준으로 한다. 주 옵션 (Main Stats) 각 계시 위치 별로 나올 수 있는 주 옵션이 고정돼 있다. 위치옵션주 (Universe)공격력, 방어력일 (Sun)생명월 (Moon)공격력, 대미지 보너스, 생명, 방어력, 치료 효과성 (Star)크리티컬 확률, 크리티컬 효과, 생명, 공격력, 방어력, 효과 명중진 (Sky)공격력, 방어력, 생명, SP 회복, 속도 일반적으로 메인 스탯의 최댓값이 높은 관계로, 메인 스탯을 챙긴 이후 부 옵션을 고려하는 편이 좋다. 주 (Universe) 옵션최소최대공격력54359방어력54359 부 옵션 (Sub Stats) 각 계시는 생성될 때 3~4개의 부가 옵션을 가지고 나타난다. 부가 옵션은 랜덤하게 결정되며, 수치 또한 랜덤하게 결정되나 각 스탯 별로 최소값과 최고값이 존재한다. 대부분의 딜러는 크리티컬 확률 크리티컬 효과 관통 대미지 보너스 공격력 % 공격력 상수 해당 6개가 주요한 서브 스탯으로 취급된다. 아래는 각 계시별 나타날 수 있는 서브스탯 수치 값 주 (Universe) 옵션1st2nd3rd4th5th크리티컬 확률2.6%2.3%2.1%1.8%1.6%크리티컬 효과5.2%4.7%4.1%3.6%3.1%관통2.7%2.5%2.2%1.8%1.6%대미지 보너스3.5%3.1%2.6%2.2%1.8%공격력%4.3%3.9%3.5%3.1%2.6%공격력/////생명%4.4%4.0%3.5%3.2%2.7%생명175157140123105방어력%6.4%5.8%5.2%4.5%3.8%방어력/////효과 명중5.2%4.7%4.1%3.6%3.1%SP회복12.5%11.2%10.0%8.7%7.5%속도2.82.52.21.91.6 일월성진 (Sun/Moon/Star/Sky) 옵션1st2nd3rd4th5th크리티컬 확률2%1.8%1.7%1.4%1.3%크리티컬 효과4.1%3.7%3.4%2.8%2.5%관통2.1%1.9%1.7%1.4%1.3%대미지 보너스2.8%2.5%2.1%1.9%1.7%공격력%3.5%3.2%2.8%2.5%2.0%공격력4641373227생명%3.6%3.3%2.9%2.6%2.1%생명1401261129884방어력%5.2%4.6%4.1%3.5%3.0%방어력4641373227효과 명중4.1%3.7%3.4%2.8%2.5%SP회복10.0%9.0%7.9%7.0%5.9%속도2.221.81.51.3 소숫점 값이 더 있으나 소숫점 1자리로 처리된 값에 따라 표기된다. 계시 세트 옵션은 여기를 참고하세요.",
    "en": "Stats are based on the yellow revelation cards starting at Lv1 to Lv25 Main Stats Each revelation position has fixed main stats that can appear. PositionOptionsUniverseAttack, DefenseSunHPMoonAttack, Damage Mult, HP, Defense, Healing EffectStarCrit Rate, Crit Mult., HP, Attack, Defense, Ailment AccuracySkyAttack, Defense, HP, SP Recovery, Speed Generally, since main stats have higher maximum values, it's better to prioritize main stats before considering sub stats. Sub Stats Each revelation appears with 3-4 additional sub stats when generated. Sub stats are randomly determined, and their values are also random, but each stat has minimum and maximum values. For most DPS characters, the following 6 stats are considered major sub stats: Crit Rate Crit Mult. Pierce Rate Damage Mult Attack % Attack (Flat) Below are the sub stat values that can appear on each revelation: Universe Option1st2nd3rd4th5thCrit Rate2.6%2.3%2.1%1.8%1.6%Crit Mult.5.2%4.7%4.1%3.6%3.1%Pierce Rate2.7%2.5%2.2%1.8%1.6%Damage Mult3.5%3.1%2.6%2.2%1.8%Attack %4.3%3.9%3.5%3.1%2.6%Attack/////HP %4.4%4.0%3.5%3.2%2.7%HP175157140123105Defense %6.4%5.8%5.2%4.5%3.8%Defense/////Ailment Accuracy5.2%4.7%4.1%3.6%3.1%SP Recovery12.5%11.2%10.0%8.7%7.5%Speed2.82.52.21.91.6 Sun/Moon/Star/Sky Option1st2nd3rd4th5thCrit Rate2%1.8%1.7%1.4%1.3%Crit Mult.4.1%3.7%3.4%2.8%2.5%Pierce Rate2.1%1.9%1.7%1.4%1.3%Damage Mult2.8%2.5%2.1%1.9%1.7%Attack %3.5%3.2%2.8%2.5%2.0%Attack4641373227HP %3.6%3.3%2.9%2.6%2.1%HP1401261129884Defense %5.2%4.6%4.1%3.5%3.0%Defense4641373227Ailment Accuracy4.1%3.7%3.4%2.8%2.5%SP Recovery10.0%9.0%7.9%7.0%5.9%Speed2.221.81.51.3 There are more decimal values, but they are displayed according to values processed to 1 decimal place. For revelation set options, please refer here.",
    "jp": "すべてのステータスの数値はレベル1からレベル25までの黄色の啓示カードを基準にしています。 メインステータス 各啓示のポジション別に出現可能な主属性が固定されています。 ポジションオプション主 (Universe)攻撃力、防御力旭 (Sun)HP月 (Moon)攻撃力、攻撃倍率+、HP、防御力、HP回復量星 (Star)CRT発生率、CRT倍率、HP、攻撃力、防御力、状態異常命中天 (Sky)攻撃力、防御力、HP、SP回復、速さ 一般的にメインステータスの最大値が高いため、メインステータスを確保した後にサブオプションを考慮するのが良いでしょう。 サブステータス 各啓示は生成時に3～4個の追加オプションを持って現れます。 追加オプションはランダムに決定され、数値もランダムに決定されますが、各ステータス別に最小値と最大値が存在します。 ほとんどのディーラーにとって、以下の6つが主要なサブステータスとして扱われます： CRT発生率 CRT倍率 貫通 攻撃倍率+ 攻撃力 % 攻撃力（固定値） 以下は各啓示別に出現可能なサブステータス数値です： 宙 オプション1st2nd3rd4th5thCRT発生率2.6%2.3%2.1%1.8%1.6%CRT倍率5.2%4.7%4.1%3.6%3.1%貫通2.7%2.5%2.2%1.8%1.6%攻撃倍率+3.5%3.1%2.6%2.2%1.8%攻撃力%4.3%3.9%3.5%3.1%2.6%攻撃力/////HP%4.4%4.0%3.5%3.2%2.7%HP175157140123105防御力%6.4%5.8%5.2%4.5%3.8%防御力/////状態異常命中5.2%4.7%4.1%3.6%3.1%SP回復12.5%11.2%10.0%8.7%7.5%速さ2.82.52.21.91.6 旭月星天 オプション1st2nd3rd4th5thCRT発生率2%1.8%1.7%1.4%1.3%CRT倍率4.1%3.7%3.4%2.8%2.5%貫通2.1%1.9%1.7%1.4%1.3%攻撃倍率+2.8%2.5%2.1%1.9%1.7%攻撃力%3.5%3.2%2.8%2.5%2.0%攻撃力4641373227HP%3.6%3.3%2.9%2.6%2.1%HP1401261129884防御力%5.2%4.6%4.1%3.5%3.0%防御力4641373227状態異常命中4.1%3.7%3.4%2.8%2.5%SP回復10.0%9.0%7.9%7.0%5.9%速さ2.221.81.51.3 小数点以下の値はより多く存在しますが、小数点1桁で処理された値に従って表記されています。 啓示セットオプションについては、こちらを参照してください。"
  },
  "category": "system",
  "tags": [
    "guide"
  ],
  "date": "2025-07-11",
  "author": "AbsolRoot",
  "thumbnail": "/apps/guides/data/assets/Revelation-Options/damage4-1.png",
  "contents": {
    "kr": "<p>모든 스탯 수치는 레벨 1부터 레벨 25까지 노란색 계시 카드를 기준으로 한다.</p>\n<p><br></p>\n<h1>주 옵션 (Main Stats)</h1>\n<p>각 계시 위치 별로 나올 수 있는 주 옵션이 고정돼 있다.</p>\n<table><thead><tr><th>위치</th><th>옵션</th></tr></thead><tbody><tr><td>주 (Universe)</td><td>공격력, 방어력</td></tr><tr><td>일 (Sun)</td><td>생명</td></tr><tr><td>월 (Moon)</td><td>공격력, 대미지 보너스, 생명, 방어력, 치료 효과</td></tr><tr><td>성 (Star)</td><td>크리티컬 확률, 크리티컬 효과, 생명, 공격력, 방어력, 효과 명중</td></tr><tr><td>진 (Sky)</td><td>공격력, 방어력, 생명, SP 회복, 속도</td></tr></tbody></table>\n<p>일반적으로 메인 스탯의 최댓값이 높은 관계로, 메인 스탯을 챙긴 이후 부 옵션을 고려하는 편이 좋다.</p>\n<h3>주 (Universe)</h3>\n<table><thead><tr><th>옵션</th><th>최소</th><th>최대</th></tr></thead><tbody><tr><td>공격력</td><td>54</td><td>359</td></tr><tr><td>방어력</td><td>54</td><td>359</td></tr></tbody></table>\n<hr>\n<h1>부 옵션 (Sub Stats)</h1>\n<p>각 계시는 생성될 때 3~4개의 부가 옵션을 가지고 나타난다.</p>\n<p>부가 옵션은 랜덤하게 결정되며, 수치 또한 랜덤하게 결정되나 각 스탯 별로 최소값과 최고값이 존재한다.</p>\n<p>대부분의 딜러는</p>\n<ul><li>크리티컬 확률</li>\n<li>크리티컬 효과</li>\n<li>관통</li>\n<li>대미지 보너스</li>\n<li>공격력 %</li>\n<li>공격력 상수</li>\n</ul>\n해당 6개가 주요한 서브 스탯으로 취급된다.\n<p>아래는 각 계시별 나타날 수 있는 서브스탯 수치 값</p>\n<p><br></p>\n<h3>주 (Universe)</h3>\n<table><thead><tr><th>옵션</th><th>1st</th><th>2nd</th><th>3rd</th><th>4th</th><th>5th</th></tr></thead><tbody><tr><td><strong>크리티컬 확률</strong></td><td>2.6%</td><td>2.3%</td><td>2.1%</td><td>1.8%</td><td>1.6%</td></tr><tr><td><strong>크리티컬 효과</strong></td><td>5.2%</td><td>4.7%</td><td>4.1%</td><td>3.6%</td><td>3.1%</td></tr><tr><td><strong>관통</strong></td><td>2.7%</td><td>2.5%</td><td>2.2%</td><td>1.8%</td><td>1.6%</td></tr><tr><td><strong>대미지 보너스</strong></td><td>3.5%</td><td>3.1%</td><td>2.6%</td><td>2.2%</td><td>1.8%</td></tr><tr><td><strong>공격력%</strong></td><td>4.3%</td><td>3.9%</td><td>3.5%</td><td>3.1%</td><td>2.6%</td></tr><tr><td><strong>공격력</strong></td><td>/</td><td>/</td><td>/</td><td>/</td><td>/</td></tr><tr><td><strong>생명%</strong></td><td>4.4%</td><td>4.0%</td><td>3.5%</td><td>3.2%</td><td>2.7%</td></tr><tr><td><strong>생명</strong></td><td>175</td><td>157</td><td>140</td><td>123</td><td>105</td></tr><tr><td><strong>방어력%</strong></td><td>6.4%</td><td>5.8%</td><td>5.2%</td><td>4.5%</td><td>3.8%</td></tr><tr><td><strong>방어력</strong></td><td>/</td><td>/</td><td>/</td><td>/</td><td>/</td></tr><tr><td><strong>효과 명중</strong></td><td>5.2%</td><td>4.7%</td><td>4.1%</td><td>3.6%</td><td>3.1%</td></tr><tr><td><strong>SP회복</strong></td><td>12.5%</td><td>11.2%</td><td>10.0%</td><td>8.7%</td><td>7.5%</td></tr><tr><td><strong>속도</strong></td><td>2.8</td><td>2.5</td><td>2.2</td><td>1.9</td><td>1.6</td></tr></tbody></table>\n<p><br></p>\n<h3>일월성진 (Sun/Moon/Star/Sky)</h3>\n<table><thead><tr><th>옵션</th><th>1st</th><th>2nd</th><th>3rd</th><th>4th</th><th>5th</th></tr></thead><tbody><tr><td><strong>크리티컬 확률</strong></td><td>2%</td><td>1.8%</td><td>1.7%</td><td>1.4%</td><td>1.3%</td></tr><tr><td><strong>크리티컬 효과</strong></td><td>4.1%</td><td>3.7%</td><td>3.4%</td><td>2.8%</td><td>2.5%</td></tr><tr><td><strong>관통</strong></td><td>2.1%</td><td>1.9%</td><td>1.7%</td><td>1.4%</td><td>1.3%</td></tr><tr><td><strong>대미지 보너스</strong></td><td>2.8%</td><td>2.5%</td><td>2.1%</td><td>1.9%</td><td>1.7%</td></tr><tr><td><strong>공격력%</strong></td><td>3.5%</td><td>3.2%</td><td>2.8%</td><td>2.5%</td><td>2.0%</td></tr><tr><td><strong>공격력</strong></td><td>46</td><td>41</td><td>37</td><td>32</td><td>27</td></tr><tr><td><strong>생명%</strong></td><td>3.6%</td><td>3.3%</td><td>2.9%</td><td>2.6%</td><td>2.1%</td></tr><tr><td><strong>생명</strong></td><td>140</td><td>126</td><td>112</td><td>98</td><td>84</td></tr><tr><td><strong>방어력%</strong></td><td>5.2%</td><td>4.6%</td><td>4.1%</td><td>3.5%</td><td>3.0%</td></tr><tr><td><strong>방어력</strong></td><td>46</td><td>41</td><td>37</td><td>32</td><td>27</td></tr><tr><td><strong>효과 명중</strong></td><td>4.1%</td><td>3.7%</td><td>3.4%</td><td>2.8%</td><td>2.5%</td></tr><tr><td><strong>SP회복</strong></td><td>10.0%</td><td>9.0%</td><td>7.9%</td><td>7.0%</td><td>5.9%</td></tr><tr><td><strong>속도</strong></td><td>2.2</td><td>2</td><td>1.8</td><td>1.5</td><td>1.3</td></tr></tbody></table>\n<p>소숫점 값이 더 있으나 소숫점 1자리로 처리된 값에 따라 표기된다.</p>\n<hr>\n<p><strong>계시 세트 옵션은 <a href=\"https://lufel.net/revelations\">여기</a>를 참고하세요.</strong></p>\n<p><br></p>",
    "en": "<p>Stats are based on the yellow revelation cards starting at Lv1 to Lv25</p>\n<p><br></p>\n<h1>Main Stats</h1>\n<p>Each revelation position has fixed main stats that can appear.</p>\n<table><thead><tr><th>Position</th><th>Options</th></tr></thead><tbody><tr><td>Universe</td><td>Attack, Defense</td></tr><tr><td>Sun</td><td>HP</td></tr><tr><td>Moon</td><td>Attack, Damage Mult, HP, Defense, Healing Effect</td></tr><tr><td>Star</td><td>Crit Rate, Crit Mult., HP, Attack, Defense, Ailment Accuracy</td></tr><tr><td>Sky</td><td>Attack, Defense, HP, SP Recovery, Speed</td></tr></tbody></table>\n<p>Generally, since main stats have higher maximum values, it's better to prioritize main stats before considering sub stats.</p>\n<hr>\n<h1>Sub Stats</h1>\n<p>Each revelation appears with 3-4 additional sub stats when generated.</p>\n<p>Sub stats are randomly determined, and their values are also random, but each stat has minimum and maximum values.</p>\n<p>For most DPS characters, the following 6 stats are considered major sub stats:</p>\n<ul><li>Crit Rate</li>\n<li>Crit Mult.</li>\n<li>Pierce Rate</li>\n<li>Damage Mult</li>\n<li>Attack %</li>\n<li>Attack (Flat)</li>\n</ul>\nBelow are the sub stat values that can appear on each revelation:\n<p><br></p>\n<h3>Universe</h3>\n<table><thead><tr><th>Option</th><th>1st</th><th>2nd</th><th>3rd</th><th>4th</th><th>5th</th></tr></thead><tbody><tr><td><strong>Crit Rate</strong></td><td>2.6%</td><td>2.3%</td><td>2.1%</td><td>1.8%</td><td>1.6%</td></tr><tr><td><strong>Crit Mult.</strong></td><td>5.2%</td><td>4.7%</td><td>4.1%</td><td>3.6%</td><td>3.1%</td></tr><tr><td><strong>Pierce Rate</strong></td><td>2.7%</td><td>2.5%</td><td>2.2%</td><td>1.8%</td><td>1.6%</td></tr><tr><td><strong>Damage Mult</strong></td><td>3.5%</td><td>3.1%</td><td>2.6%</td><td>2.2%</td><td>1.8%</td></tr><tr><td><strong>Attack %</strong></td><td>4.3%</td><td>3.9%</td><td>3.5%</td><td>3.1%</td><td>2.6%</td></tr><tr><td><strong>Attack</strong></td><td>/</td><td>/</td><td>/</td><td>/</td><td>/</td></tr><tr><td><strong>HP %</strong></td><td>4.4%</td><td>4.0%</td><td>3.5%</td><td>3.2%</td><td>2.7%</td></tr><tr><td><strong>HP</strong></td><td>175</td><td>157</td><td>140</td><td>123</td><td>105</td></tr><tr><td><strong>Defense %</strong></td><td>6.4%</td><td>5.8%</td><td>5.2%</td><td>4.5%</td><td>3.8%</td></tr><tr><td><strong>Defense</strong></td><td>/</td><td>/</td><td>/</td><td>/</td><td>/</td></tr><tr><td><strong>Ailment Accuracy</strong></td><td>5.2%</td><td>4.7%</td><td>4.1%</td><td>3.6%</td><td>3.1%</td></tr><tr><td><strong>SP Recovery</strong></td><td>12.5%</td><td>11.2%</td><td>10.0%</td><td>8.7%</td><td>7.5%</td></tr><tr><td><strong>Speed</strong></td><td>2.8</td><td>2.5</td><td>2.2</td><td>1.9</td><td>1.6</td></tr></tbody></table>\n<p><br></p>\n<h3>Sun/Moon/Star/Sky</h3>\n<table><thead><tr><th>Option</th><th>1st</th><th>2nd</th><th>3rd</th><th>4th</th><th>5th</th></tr></thead><tbody><tr><td><strong>Crit Rate</strong></td><td>2%</td><td>1.8%</td><td>1.7%</td><td>1.4%</td><td>1.3%</td></tr><tr><td><strong>Crit Mult.</strong></td><td>4.1%</td><td>3.7%</td><td>3.4%</td><td>2.8%</td><td>2.5%</td></tr><tr><td><strong>Pierce Rate</strong></td><td>2.1%</td><td>1.9%</td><td>1.7%</td><td>1.4%</td><td>1.3%</td></tr><tr><td><strong>Damage Mult</strong></td><td>2.8%</td><td>2.5%</td><td>2.1%</td><td>1.9%</td><td>1.7%</td></tr><tr><td><strong>Attack %</strong></td><td>3.5%</td><td>3.2%</td><td>2.8%</td><td>2.5%</td><td>2.0%</td></tr><tr><td><strong>Attack</strong></td><td>46</td><td>41</td><td>37</td><td>32</td><td>27</td></tr><tr><td><strong>HP %</strong></td><td>3.6%</td><td>3.3%</td><td>2.9%</td><td>2.6%</td><td>2.1%</td></tr><tr><td><strong>HP</strong></td><td>140</td><td>126</td><td>112</td><td>98</td><td>84</td></tr><tr><td><strong>Defense %</strong></td><td>5.2%</td><td>4.6%</td><td>4.1%</td><td>3.5%</td><td>3.0%</td></tr><tr><td><strong>Defense</strong></td><td>46</td><td>41</td><td>37</td><td>32</td><td>27</td></tr><tr><td><strong>Ailment Accuracy</strong></td><td>4.1%</td><td>3.7%</td><td>3.4%</td><td>2.8%</td><td>2.5%</td></tr><tr><td><strong>SP Recovery</strong></td><td>10.0%</td><td>9.0%</td><td>7.9%</td><td>7.0%</td><td>5.9%</td></tr><tr><td><strong>Speed</strong></td><td>2.2</td><td>2</td><td>1.8</td><td>1.5</td><td>1.3</td></tr></tbody></table>\n<p>There are more decimal values, but they are displayed according to values processed to 1 decimal place.</p>\n<hr>\n<p><strong>For revelation set options, please refer <a href=\"https://lufel.net/revelations\">here</a>.</strong></p>\n<p><br></p>",
    "jp": "<p>すべてのステータスの数値はレベル1からレベル25までの黄色の啓示カードを基準にしています。</p>\n<p><br></p>\n<h1>メインステータス</h1>\n<p>各啓示のポジション別に出現可能な主属性が固定されています。</p>\n<table><thead><tr><th>ポジション</th><th>オプション</th></tr></thead><tbody><tr><td>主 (Universe)</td><td>攻撃力、防御力</td></tr><tr><td>旭 (Sun)</td><td>HP</td></tr><tr><td>月 (Moon)</td><td>攻撃力、攻撃倍率+、HP、防御力、HP回復量</td></tr><tr><td>星 (Star)</td><td>CRT発生率、CRT倍率、HP、攻撃力、防御力、状態異常命中</td></tr><tr><td>天 (Sky)</td><td>攻撃力、防御力、HP、SP回復、速さ</td></tr></tbody></table>\n<p>一般的にメインステータスの最大値が高いため、メインステータスを確保した後にサブオプションを考慮するのが良いでしょう。</p>\n<hr>\n<h1>サブステータス</h1>\n<p>各啓示は生成時に3～4個の追加オプションを持って現れます。</p>\n<p>追加オプションはランダムに決定され、数値もランダムに決定されますが、各ステータス別に最小値と最大値が存在します。</p>\n<p>ほとんどのディーラーにとって、以下の6つが主要なサブステータスとして扱われます：</p>\n<ul><li>CRT発生率</li>\n<li>CRT倍率</li>\n<li>貫通</li>\n<li>攻撃倍率+</li>\n<li>攻撃力 %</li>\n<li>攻撃力（固定値）</li>\n</ul>\n以下は各啓示別に出現可能なサブステータス数値です：\n<p><br></p>\n<h3>宙</h3>\n<table><thead><tr><th>オプション</th><th>1st</th><th>2nd</th><th>3rd</th><th>4th</th><th>5th</th></tr></thead><tbody><tr><td><strong>CRT発生率</strong></td><td>2.6%</td><td>2.3%</td><td>2.1%</td><td>1.8%</td><td>1.6%</td></tr><tr><td><strong>CRT倍率</strong></td><td>5.2%</td><td>4.7%</td><td>4.1%</td><td>3.6%</td><td>3.1%</td></tr><tr><td><strong>貫通</strong></td><td>2.7%</td><td>2.5%</td><td>2.2%</td><td>1.8%</td><td>1.6%</td></tr><tr><td><strong>攻撃倍率+</strong></td><td>3.5%</td><td>3.1%</td><td>2.6%</td><td>2.2%</td><td>1.8%</td></tr><tr><td><strong>攻撃力%</strong></td><td>4.3%</td><td>3.9%</td><td>3.5%</td><td>3.1%</td><td>2.6%</td></tr><tr><td><strong>攻撃力</strong></td><td>/</td><td>/</td><td>/</td><td>/</td><td>/</td></tr><tr><td><strong>HP%</strong></td><td>4.4%</td><td>4.0%</td><td>3.5%</td><td>3.2%</td><td>2.7%</td></tr><tr><td><strong>HP</strong></td><td>175</td><td>157</td><td>140</td><td>123</td><td>105</td></tr><tr><td><strong>防御力%</strong></td><td>6.4%</td><td>5.8%</td><td>5.2%</td><td>4.5%</td><td>3.8%</td></tr><tr><td><strong>防御力</strong></td><td>/</td><td>/</td><td>/</td><td>/</td><td>/</td></tr><tr><td><strong>状態異常命中</strong></td><td>5.2%</td><td>4.7%</td><td>4.1%</td><td>3.6%</td><td>3.1%</td></tr><tr><td><strong>SP回復</strong></td><td>12.5%</td><td>11.2%</td><td>10.0%</td><td>8.7%</td><td>7.5%</td></tr><tr><td><strong>速さ</strong></td><td>2.8</td><td>2.5</td><td>2.2</td><td>1.9</td><td>1.6</td></tr></tbody></table>\n<p><br></p>\n<h3>旭月星天</h3>\n<table><thead><tr><th>オプション</th><th>1st</th><th>2nd</th><th>3rd</th><th>4th</th><th>5th</th></tr></thead><tbody><tr><td><strong>CRT発生率</strong></td><td>2%</td><td>1.8%</td><td>1.7%</td><td>1.4%</td><td>1.3%</td></tr><tr><td><strong>CRT倍率</strong></td><td>4.1%</td><td>3.7%</td><td>3.4%</td><td>2.8%</td><td>2.5%</td></tr><tr><td><strong>貫通</strong></td><td>2.1%</td><td>1.9%</td><td>1.7%</td><td>1.4%</td><td>1.3%</td></tr><tr><td><strong>攻撃倍率+</strong></td><td>2.8%</td><td>2.5%</td><td>2.1%</td><td>1.9%</td><td>1.7%</td></tr><tr><td><strong>攻撃力%</strong></td><td>3.5%</td><td>3.2%</td><td>2.8%</td><td>2.5%</td><td>2.0%</td></tr><tr><td><strong>攻撃力</strong></td><td>46</td><td>41</td><td>37</td><td>32</td><td>27</td></tr><tr><td><strong>HP%</strong></td><td>3.6%</td><td>3.3%</td><td>2.9%</td><td>2.6%</td><td>2.1%</td></tr><tr><td><strong>HP</strong></td><td>140</td><td>126</td><td>112</td><td>98</td><td>84</td></tr><tr><td><strong>防御力%</strong></td><td>5.2%</td><td>4.6%</td><td>4.1%</td><td>3.5%</td><td>3.0%</td></tr><tr><td><strong>防御力</strong></td><td>46</td><td>41</td><td>37</td><td>32</td><td>27</td></tr><tr><td><strong>状態異常命中</strong></td><td>4.1%</td><td>3.7%</td><td>3.4%</td><td>2.8%</td><td>2.5%</td></tr><tr><td><strong>SP回復</strong></td><td>10.0%</td><td>9.0%</td><td>7.9%</td><td>7.0%</td><td>5.9%</td></tr><tr><td><strong>速さ</strong></td><td>2.2</td><td>2</td><td>1.8</td><td>1.5</td><td>1.3</td></tr></tbody></table>\n<p>小数点以下の値はより多く存在しますが、小数点1桁で処理された値に従って表記されています。</p>\n<hr>\n<p><strong>啓示セットオプションについては、<a href=\"https://lufel.net/revelations\">こちら</a>を参照してください。</strong></p>\n<p><br></p>"
  }
}