{
  "data": {
    "advance_dialog": [
      {
        "good_answers": [
          [
            {
              "content": "一理ある",
              "reward": 60
            },
            {
              "content": "ただの屁理屈のような…",
              "reward": 40
            },
            {
              "content": "周りの視線は気にならない？",
              "reward": 50
            }
          ]
        ],
        "rank_up": {
          "from": 2,
          "to": 3
        },
        "unlock_cond": "知識 Lv.3"
      },
      {
        "good_answers": [
          [
            {
              "content": "話が早すぎる…",
              "reward": 50
            },
            {
              "content": "実験の趣旨は？",
              "reward": 60
            },
            {
              "content": "断ったら？",
              "reward": 40
            }
          ]
        ],
        "rank_up": {
          "from": 4,
          "to": 5
        },
        "unlock_cond": "知識 Lv.5"
      },
      {
        "good_answers": [
          [
            {
              "content": "いいお姉さんだ",
              "reward": 60
            },
            {
              "content": "嫌いなの？",
              "reward": 40
            },
            {
              "content": "紹介してほしい",
              "reward": 50
            }
          ]
        ],
        "rank_up": {
          "from": 6,
          "to": 7
        },
        "unlock_cond": "知識 Lv.6"
      },
      {
        "good_answers": [
          [
            {
              "content": "任せろ",
              "reward": 60
            },
            {
              "content": "逆の方がいいんじゃ…",
              "reward": 50
            },
            {
              "content": "作戦なんて必要ない",
              "reward": 40
            }
          ]
        ],
        "rank_up": {
          "from": 8,
          "to": 9
        },
        "unlock_cond": "知識 Lv.8"
      },
      {
        "good_answers": [
          [
            {
              "content": "患者の自由だ",
              "reward": 50
            },
            {
              "content": "基良の気持ちはわかる",
              "reward": 60
            },
            {
              "content": "追加注文していい？",
              "reward": 40
            }
          ]
        ],
        "rank_up": {
          "from": 10,
          "to": 11
        },
        "unlock_cond": "知識 Lv.10"
      },
      {
        "good_answers": [
          [
            {
              "content": "もう諦めるの？",
              "reward": 50
            },
            {
              "content": "気合が足りない",
              "reward": 40
            },
            {
              "content": "気持ちを全部ぶつけるべき",
              "reward": 60
            }
          ]
        ],
        "rank_up": {
          "from": 12,
          "to": 13
        },
        "unlock_cond": "知識 Lv.11"
      },
      {
        "good_answers": [
          [
            {
              "content": "考えすぎだと思う",
              "reward": 40
            },
            {
              "content": "信じてみよう",
              "reward": 50
            },
            {
              "content": "罠でも利用すればいい",
              "reward": 60
            }
          ]
        ],
        "rank_up": {
          "from": 14,
          "to": 15
        },
        "unlock_cond": "知識 Lv.13"
      },
      {
        "good_answers": [
          [
            {
              "content": "逃げるのか？",
              "reward": 50
            },
            {
              "content": "１度落ち着こう",
              "reward": 60
            },
            {
              "content": "今からでは遅い",
              "reward": 40
            }
          ]
        ],
        "rank_up": {
          "from": 16,
          "to": 17
        },
        "unlock_cond": "知識 Lv.15"
      },
      {
        "good_answers": [
          [
            {
              "content": "仕方ない…",
              "reward": 40
            },
            {
              "content": "拒否権は？",
              "reward": 50
            },
            {
              "content": "『取引』はまだ有効だから",
              "reward": 60
            }
          ]
        ],
        "rank_up": {
          "from": 19,
          "to": 20
        },
        "unlock_cond": "知識 Lv.17"
      }
    ],
    "can_romance": false,
    "friend_lover_dialog": [],
    "item": [
      {
        "bonus_synergy": 8,
        "compound": [],
        "image": "item-303068.png",
        "name": "スポーツ用吸水タオル",
        "new_gift_synergy": 16,
        "seed": [],
        "shop": [
          {
            "isHidden": 0,
            "mapName": null,
            "maxBuy": 1,
            "moneyName": "バッティングポイント",
            "price": 500,
            "resetType": "없음",
            "shopName": "バッティングポイント交換"
          },
          {
            "isHidden": 0,
            "mapName": null,
            "maxBuy": 4,
            "moneyName": "所持金",
            "price": 3000,
            "resetType": "주간",
            "shopName": "大正屋"
          }
        ],
        "source": [
          "shop"
        ],
        "synergy": 8
      },
      {
        "bonus_synergy": 16,
        "compound": [],
        "image": "item-303206.png",
        "name": "もっちもちクッション",
        "new_gift_synergy": 32,
        "seed": [],
        "shop": [
          {
            "isHidden": 0,
            "mapName": null,
            "maxBuy": 1,
            "moneyName": "所持金",
            "personalityLimit": "優しさ LV.12",
            "price": 6500,
            "resetType": "주간",
            "shopName": "トリプルセブン"
          }
        ],
        "source": [
          "shop"
        ],
        "synergy": 16
      },
      {
        "bonus_synergy": 15,
        "compound": [],
        "image": "item-303209.png",
        "name": "多面立方体パズル",
        "new_gift_synergy": 30,
        "seed": [],
        "shop": [
          {
            "isHidden": 0,
            "mapName": null,
            "maxBuy": 1,
            "moneyName": "所持金",
            "personalityLimit": "知識 LV.3",
            "price": 5800,
            "resetType": "주간",
            "shopName": "トリプルセブン"
          }
        ],
        "source": [
          "shop"
        ],
        "synergy": 15
      },
      {
        "bonus_synergy": 37,
        "compound": [],
        "image": "item-303232.png",
        "name": "高級サングラス",
        "new_gift_synergy": 74,
        "seed": [],
        "shop": [
          {
            "isHidden": 0,
            "mapName": null,
            "maxBuy": 1,
            "moneyName": "所持金",
            "price": 18000,
            "resetType": "주간",
            "shopName": "３７℃"
          }
        ],
        "source": [
          "shop"
        ],
        "synergy": 37
      },
      {
        "bonus_synergy": 18,
        "compound": [],
        "image": "item-303235.png",
        "name": "超爆音目覚まし時計",
        "new_gift_synergy": 36,
        "seed": [],
        "shop": [
          {
            "isHidden": 0,
            "mapName": null,
            "maxBuy": 1,
            "moneyName": "所持金",
            "price": 7000,
            "resetType": "주간",
            "shopName": "ロシナンテ"
          }
        ],
        "source": [
          "shop"
        ],
        "synergy": 18
      },
      {
        "bonus_synergy": 11,
        "compound": [],
        "image": "item-303277.png",
        "name": "エイム上達法",
        "new_gift_synergy": 22,
        "seed": [],
        "shop": [
          {
            "isHidden": 0,
            "mapName": null,
            "maxBuy": 3,
            "moneyName": "所持金",
            "price": 4500,
            "resetType": "주간",
            "shopName": "文房具屋"
          }
        ],
        "source": [
          "shop"
        ],
        "synergy": 11
      },
      {
        "bonus_synergy": 8,
        "compound": [],
        "image": "item-303278.png",
        "name": "大容量魔法瓶",
        "new_gift_synergy": 16,
        "seed": [],
        "shop": [
          {
            "isHidden": 0,
            "mapName": null,
            "maxBuy": 3,
            "moneyName": "所持金",
            "price": 3000,
            "resetType": "주간",
            "shopName": "雑司ヶ谷マート"
          }
        ],
        "source": [
          "shop"
        ],
        "synergy": 8
      },
      {
        "bonus_synergy": 40,
        "compound": [],
        "image": "item-303279.png",
        "name": "ソルジャーフィギュア",
        "new_gift_synergy": 80,
        "seed": [],
        "shop": [
          {
            "isHidden": 0,
            "mapName": null,
            "maxBuy": 1,
            "moneyName": "所持金",
            "price": 20000,
            "resetType": "주간",
            "shopName": "ロシナンテ"
          }
        ],
        "source": [
          "shop"
        ],
        "synergy": 40
      },
      {
        "bonus_synergy": 20,
        "compound": [],
        "image": "item-303280.png",
        "name": "眼精疲労用目薬",
        "new_gift_synergy": 40,
        "seed": [],
        "shop": [
          {
            "isHidden": 0,
            "mapName": null,
            "maxBuy": 2,
            "moneyName": "所持金",
            "price": 8000,
            "resetType": "주간",
            "shopName": "ＡＯＨＩＧＥ"
          }
        ],
        "source": [
          "shop"
        ],
        "synergy": 20
      },
      {
        "bonus_synergy": 52,
        "compound": [],
        "image": "item-303281.png",
        "name": "ひげメガネ",
        "new_gift_synergy": 104,
        "seed": [],
        "shop": [
          {
            "isHidden": 0,
            "mapName": null,
            "maxBuy": 1,
            "moneyName": "所持金",
            "price": 30000,
            "resetType": "주간",
            "shopName": "３７℃"
          }
        ],
        "source": [
          "shop"
        ],
        "synergy": 52
      },
      {
        "bonus_synergy": 8,
        "compound": [],
        "image": "item-303282.png",
        "name": "限定版キーホルダー",
        "new_gift_synergy": 16,
        "seed": [],
        "shop": [
          {
            "discountPrice": 3000,
            "isHidden": 0,
            "mapName": null,
            "maxBuy": 3,
            "moneyName": "所持金",
            "price": 3000,
            "reducePriceCond": "道玄坂琉七 LV.13",
            "resetType": "주간",
            "shopName": "パワーストーン専門店"
          }
        ],
        "source": [
          "shop"
        ],
        "synergy": 8
      },
      {
        "bonus_synergy": 8,
        "compound": [],
        "image": "item-303283.png",
        "name": "お菓子袋詰めセット",
        "new_gift_synergy": 16,
        "seed": [],
        "shop": [
          {
            "discountPrice": 3000,
            "isHidden": 0,
            "mapName": null,
            "maxBuy": 3,
            "moneyName": "所持金",
            "price": 3000,
            "reducePriceCond": "道玄坂琉七 LV.9",
            "resetType": "주간",
            "shopName": "スーパームラマサ"
          }
        ],
        "source": [
          "shop"
        ],
        "synergy": 8
      },
      {
        "bonus_synergy": 19,
        "compound": [],
        "image": "item-303284.png",
        "name": "エッセンシャルオイル",
        "new_gift_synergy": 38,
        "seed": [],
        "shop": [
          {
            "discountPrice": 7700,
            "isHidden": 0,
            "mapName": null,
            "maxBuy": 2,
            "moneyName": "所持金",
            "price": 7700,
            "reducePriceCond": "道玄坂琉七 LV.1",
            "resetType": "주간",
            "shopName": "ボディチョップ"
          }
        ],
        "source": [
          "shop"
        ],
        "synergy": 19
      },
      {
        "bonus_synergy": 15,
        "compound": [],
        "image": "item-303285.png",
        "name": "モンブラン",
        "new_gift_synergy": 30,
        "seed": [],
        "shop": [
          {
            "discountPrice": 6000,
            "isHidden": 0,
            "mapName": null,
            "maxBuy": 3,
            "moneyName": "所持金",
            "price": 6000,
            "reducePriceCond": "道玄坂琉七 LV.1",
            "resetType": "주간",
            "shopName": "大正屋"
          }
        ],
        "source": [
          "shop"
        ],
        "synergy": 15
      },
      {
        "bonus_synergy": 24,
        "compound": [],
        "image": "item-303286.png",
        "name": "スノードーム",
        "new_gift_synergy": 48,
        "seed": [],
        "shop": [
          {
            "discountPrice": 10000,
            "isHidden": 0,
            "mapName": null,
            "maxBuy": 1,
            "moneyName": "所持金",
            "price": 10000,
            "reducePriceCond": "道玄坂琉七 LV.13",
            "resetType": "주간",
            "shopName": "文房具屋"
          }
        ],
        "source": [
          "shop"
        ],
        "synergy": 24
      },
      {
        "bonus_synergy": 28,
        "compound": [],
        "image": "item-303287.png",
        "name": "アロマディフューザー",
        "new_gift_synergy": 56,
        "seed": [],
        "shop": [
          {
            "discountPrice": 12000,
            "isHidden": 0,
            "mapName": null,
            "maxBuy": 1,
            "moneyName": "所持金",
            "price": 12000,
            "reducePriceCond": "道玄坂琉七 LV.1",
            "resetType": "주간",
            "shopName": "ボディチョップ"
          }
        ],
        "source": [
          "shop"
        ],
        "synergy": 28
      }
    ],
    "name": "北里基良",
    "romance_dialog": [
      {
        "good_answers": [
          [
            {
              "content": "自分で掃除している",
              "reward": 60
            },
            {
              "content": "ペットがやってくれる",
              "reward": 50
            }
          ],
          [
            {
              "content": "どうせ冗談でしょ？",
              "reward": 50
            },
            {
              "content": "タダでいいよ",
              "reward": 60
            }
          ]
        ]
      }
    ],
    "special_award": [
      {
        "description": "味方の遠隔攻撃時、与ダメージが１０％上昇する",
        "icon": "xielizhe-icon-doctor-01.png",
        "name": "装弾急げ！",
        "rank": 1
      },
      {
        "description": "味方の遠隔攻撃で弾薬が尽きた後、２ターン後に弾数が回復する",
        "icon": "xielizhe-icon-doctor-02.png",
        "name": "薬室に装填！",
        "rank": 5
      },
      {
        "description": "味方の遠隔攻撃時、銃撃属性の与ダメージが１０％上昇する",
        "icon": "xielizhe-icon-doctor-01.png",
        "name": "狙え！",
        "rank": 9
      },
      {
        "description": "味方の遠隔攻撃時、銃撃属性の与ダメージがさらに１０%上昇する",
        "icon": "xielizhe-icon-doctor-01.png",
        "name": "撃て！",
        "rank": 13
      },
      {
        "description": "味方の遠隔攻撃で弾薬が尽きた後、１ターン後に弾数が回復する",
        "icon": "xielizhe-icon-doctor-02.png",
        "name": "撃ちまくれ！",
        "rank": 17
      }
    ],
    "time": "夜",
    "unlock_quest": {
      "details": "前方に異変が発生している場所がある。\n調査しに行こう。",
      "name": "在りし日の認知の間"
    },
    "visit_dialog": [
      {
        "destination": "神田",
        "good_answers": [
          [
            {
              "content": "そういうこともあると思う",
              "reward": 50
            },
            {
              "content": "医者の腕の方が重要だ",
              "reward": 60
            }
          ]
        ]
      },
      {
        "destination": "新宿",
        "good_answers": [
          [
            {
              "content": "どんな本を期待してたの？",
              "reward": 50
            },
            {
              "content": "実は奥の方に…",
              "reward": 60
            }
          ]
        ]
      },
      {
        "destination": "吉祥寺",
        "good_answers": [
          [
            {
              "content": "モテたい",
              "reward": 40
            },
            {
              "content": "基良は？",
              "reward": 60
            }
          ]
        ]
      },
      {
        "destination": "渋谷",
        "good_answers": [
          [
            {
              "content": "値段を重視して選ぶ",
              "reward": 40
            },
            {
              "content": "特に決めてない",
              "reward": 60
            }
          ]
        ]
      },
      {
        "destination": "雑司ヶ谷",
        "good_answers": [
          [
            {
              "content": "確かに平凡な街だ",
              "reward": 40
            },
            {
              "content": "意外と面白い所もある",
              "reward": 60
            }
          ]
        ]
      }
    ]
  },
  "msg": "OK",
  "status": 0
}